pydbg.py
pydbg-0.2.1.dist-info/LICENSE
pydbg-0.2.1.dist-info/METADATA
pydbg-0.2.1.dist-info/WHEEL
pydbg-0.2.1.dist-info/top_level.txt
pydbg-0.2.1.dist-info/RECORD
