Metadata-Version: 2.1
Name: pydbg
Version: 0.2.1
Summary: Implementation of Rust2018 `dbg` builtin for Python.
Home-page: https://github.com/tylerwince/pydbg
Author: Tyler Wince
Author-email: tylerwince@gmail.com
License: MIT
Platform: UNKNOWN
Classifier: License :: OSI Approved :: MIT License
Classifier: Programming Language :: Python
Classifier: Programming Language :: Python :: 3
Classifier: Programming Language :: Python :: 3.6
Classifier: Programming Language :: Python :: Implementation :: CPython
Classifier: Programming Language :: Python :: Implementation :: PyPy
Requires-Python: >=3.6.0
